README.txt
setup.py
docs/CHANGES.txt
docs/CONTRIBUTORS.txt
docs/HISTORY.txt
docs/INSTALL.txt
docs/LICENSE.GPL
docs/LICENSE.txt
pas/__init__.py
pas.plugins.groupassigner.egg-info/PKG-INFO
pas.plugins.groupassigner.egg-info/SOURCES.txt
pas.plugins.groupassigner.egg-info/dependency_links.txt
pas.plugins.groupassigner.egg-info/entry_points.txt
pas.plugins.groupassigner.egg-info/namespace_packages.txt
pas.plugins.groupassigner.egg-info/not-zip-safe
pas.plugins.groupassigner.egg-info/paster_plugins.txt
pas.plugins.groupassigner.egg-info/requires.txt
pas.plugins.groupassigner.egg-info/top_level.txt
pas/plugins/__init__.py
pas/plugins/groupassigner/README.txt
pas/plugins/groupassigner/__init__.py
pas/plugins/groupassigner/configure.zcml
pas/plugins/groupassigner/install.py
pas/plugins/groupassigner/interface.py
pas/plugins/groupassigner/plugin.py
pas/plugins/groupassigner/tests.py
pas/plugins/groupassigner/browser/__init__.py
pas/plugins/groupassigner/browser/add_plugin.zpt
pas/plugins/groupassigner/browser/configure.zcml
pas/plugins/groupassigner/browser/icon.gif