Metadata-Version: 1.0
Name: pas.plugins.groupassigner
Version: 1.0
Summary: Assign a group to user based on an expression.
Home-page: http://www.reflab.com
Author: Riccardo Lemmi
Author-email: riccardo@reflab.com
License: GPL
Platform: UNKNOWN
Classifier: Framework :: Plone
Classifier: Intended Audience :: Developers
Classifier: Topic :: Software Development :: Libraries :: Python Modules
Classifier: License :: OSI Approved :: GNU General Public License (GPL)
